polykit/__init__.py
polykit/cli/README.md
polykit/cli/__init__.py
polykit/cli/confirm.py
polykit/cli/interrupt.py
polykit/cli/permissions.py
polykit/cli/polyargs.py
polykit/cli/progress.py
polykit/cli/walking_man.py
polykit/colors.py
polykit/core/__init__.py
polykit/core/attr_dict.py
polykit/core/decorators.py
polykit/core/deprecate.py
polykit/core/detect.py
polykit/core/main_actor.py
polykit/core/setup.py
polykit/core/singleton.py
polykit/core/traceback.py
polykit/core/type_utils.py
polykit/env/README.md
polykit/env/__init__.py
polykit/env/polyenv.py
polykit/env/types.py
polykit/files/__init__.py
polykit/files/polydiff.py
polykit/files/polyfile.py
polykit/files/types.py
polykit/log/README.md
polykit/log/__init__.py
polykit/log/formatters.py
polykit/log/polylog.py
polykit/log/time_aware.py
polykit/log/types.py
polykit/packages/__init__.py
polykit/packages/packages.py
polykit/packages/types.py
polykit/paths/README.md
polykit/paths/__init__.py
polykit/paths/polypath.py
polykit/text/__init__.py
polykit/text/markup.py
polykit/text/polycolors.py
polykit/text/polymoji.py
polykit/text/polynum.py
polykit/text/polysplit.py
polykit/text/polytext.py
polykit/text/polytruncate.py
polykit/text/text.py
polykit/text/truncate.py
polykit/text/types.py
polykit/time/__init__.py
polykit/time/polytime.py
polykit/time/time.py
polykit-0.14.5.dist-info/METADATA
polykit-0.14.5.dist-info/WHEEL
polykit-0.14.5.dist-info/licenses/LICENSE
polykit-0.14.5.dist-info/RECORD
