Metadata-Version: 2.4
Name: polykit
Version: 0.14.5
Summary: Delightful Python toolkit with power and personality 
License-Expression: LGPL-3.0-or-later
License-File: LICENSE
Author: Danny Stewart
Author-email: danny@stewart.cc
Requires-Python: >=3.12,<4.0
Classifier: Development Status :: 5 - Production/Stable
Classifier: Intended Audience :: Developers
Classifier: License :: OSI Approved :: GNU Lesser General Public License v3 or later (LGPLv3+)
Classifier: Programming Language :: Python :: 3
Classifier: Programming Language :: Python :: 3.12
Classifier: Programming Language :: Python :: 3.13
Classifier: Topic :: Software Development :: Libraries
Classifier: Topic :: Software Development :: Libraries :: Python Modules
Classifier: Topic :: System :: Shells
Classifier: Topic :: System :: System Shells
Classifier: Topic :: Utilities
Requires-Dist: halo (>=0.0.31,<0.0.32)
Requires-Dist: natsort (>=8.4.0,<9.0.0)
Requires-Dist: packaging (>=25.0,<26.0)
Requires-Dist: platformdirs (>=4.5.0,<5.0.0)
Requires-Dist: python-dateutil (>=2.9.0.post0,<3.0.0)
Requires-Dist: python-dotenv (>=1.2.1,<2.0.0)
Requires-Dist: requests (>=2.32.5,<3.0.0)
Requires-Dist: send2trash (>=1.8.3,<2.0.0)
Requires-Dist: tzlocal (>=5.3.1,<6.0.0)
